MANIFEST.in
README.md
setup.py
astar_python/__init__.py
astar_python/astar.py
astar_python.egg-info/PKG-INFO
astar_python.egg-info/SOURCES.txt
astar_python.egg-info/dependency_links.txt
astar_python.egg-info/top_level.txt