Metadata-Version: 1.1
Name: astar-python
Version: 0.1.0
Summary: A simple pathfinding eazy to use, A*
Home-page: https://github.com/zephirdeadline/astar_python
Author: Melvyn Petrocchi
Author-email: w4pity@gmail.com
License: WTFPL
Platform: UNKNOWN
Classifier: Programming Language :: Python
Classifier: Development Status :: 4 - Beta
Classifier: License :: OSI Approved
Classifier: Natural Language :: French
Classifier: Operating System :: OS Independent
Classifier: Programming Language :: Python :: 3.6
Classifier: Topic :: Software Development :: Libraries :: Python Modules
